pyabraom/__init__.py
pyabraom/pyabraom.py
PyABraOM-0.2.0.dist-info/LICENSE
PyABraOM-0.2.0.dist-info/METADATA
PyABraOM-0.2.0.dist-info/WHEEL
PyABraOM-0.2.0.dist-info/top_level.txt
PyABraOM-0.2.0.dist-info/RECORD
